{
  "trails": [
    {
      "id": "town",
      "label": "Town Trail",
      "color": "#c8a96e",
      "url": "https://streetsceal.ie/town-trail.html",
      "desc": "Voices, memories, everyday life — the Drogheda that people remember.",
      "stops": [
        {
          "id": "white-horse",
          "name": "The White Horse Hotel",
          "subtitle": "West Street, Drogheda · now The Marcy Hotel",
          "era": "1963",
          "desc": "Where Brendan Behan held court",
          "lat": 53.714978,
          "lng": -6.353384,
          "remote": false,
          "hasAudio": true,
          "hasAR": true,
          "audioSrc": "audio/white-horse.mp3",
          "tags": ["oral history", "literary", "1963"]
        },
        {
          "id": "connollys-shop",
          "name": "Connolly's Shop",
          "subtitle": "Shop Street, Drogheda · now Wogan Interiors",
          "era": "1940s–60s",
          "desc": "Commerce, community, memory",
          "lat": 53.713760,
          "lng": -6.349491,
          "remote": false,
          "hasAudio": true,
          "hasAR": true,
          "audioSrc": "audio/connollys-shop.mp3",
          "tags": ["oral history", "archive", "commerce"]
        },
        {
          "id": "millmount",
          "name": "Millmount",
          "subtitle": "Millmount Square, Drogheda",
          "era": "Ancient–present",
          "desc": "The mound that remembers everything",
          "lat": 53.711665,
          "lng": -6.349454,
          "remote": false,
          "hasAudio": false,
          "hasAR": true,
          "audioSrc": null,
          "tags": ["landscape", "history", "archaeology"],
          "linking": true
        },
        {
          "id": "laurence-gate",
          "name": "St Laurence's Gate",
          "subtitle": "Laurence Street, Drogheda",
          "era": "13th century",
          "desc": "The last gate of the walled town",
          "lat": 53.715903,
          "lng": -6.346927,
          "remote": false,
          "hasAudio": false,
          "hasAR": true,
          "audioSrc": null,
          "tags": ["medieval", "architecture", "landscape"]
        },
        {
          "id": "st-peters",
          "name": "St Peter's Church",
          "subtitle": "West Street, Drogheda",
          "era": "1921–present",
          "desc": "The National Shrine — links to the Plunkett Trail",
          "lat": 53.715034,
          "lng": -6.352422,
          "remote": false,
          "hasAudio": true,
          "hasAR": true,
          "audioSrc": "audio/GoodLuckYoungSage.wav",
          "tags": ["plunkett trail", "linking stop", "shrine"],
          "linking": true
        },
        {
          "id": "quayside",
          "name": "The Quayside",
          "subtitle": "West Gate, River Boyne, Drogheda",
          "era": "1826–1902",
          "desc": "The Steampacket era — links to the Diaspora Trail",
          "lat": 53.713810,
          "lng": -6.348835,
          "remote": false,
          "hasAudio": false,
          "hasAR": true,
          "audioSrc": null,
          "tags": ["diaspora trail", "linking stop", "steampacket"],
          "linking": true
        }
      ]
    },
    {
      "id": "plunkett",
      "label": "Plunkett Trail",
      "color": "#6ea8c8",
      "url": "https://streetsceal.ie/plunkett-trail.html",
      "desc": "A martyr's journey across Europe — from Drogheda to Ghent, Rome, London and beyond.",
      "stops": [
        {
          "id": "plunkett-quayside",
          "name": "The Quayside",
          "subtitle": "West Gate, River Boyne, Drogheda",
          "era": "Linking stop",
          "desc": "The departure point — following Plunkett out of Ireland",
          "lat": 53.713810,
          "lng": -6.348835,
          "remote": false,
          "hasAudio": false,
          "hasAR": true,
          "audioSrc": null,
          "linking": true
        },
        {
          "id": "plunkett-st-peters",
          "name": "St Peter's Church",
          "subtitle": "West Street, Drogheda",
          "era": "1921–present",
          "desc": "His head rests here — the end of a journey that crossed a continent",
          "lat": 53.715034,
          "lng": -6.352422,
          "remote": false,
          "hasAudio": true,
          "hasAR": true,
          "audioSrc": "audio/GoodLuckYoungSage.wav",
          "linking": true
        },
        {
          "id": "loughcrew",
          "name": "Loughcrew",
          "subtitle": "Oldcastle, Co. Meath",
          "era": "1625",
          "desc": "Near the Plunkett family lands in Co. Meath",
          "lat": 53.744459,
          "lng": -7.112099,
          "remote": true,
          "hasAudio": false,
          "hasAR": false,
          "audioSrc": null,
          "linking": true
        },
        {
          "id": "rome",
          "name": "Pontificio Collegio Irlandese",
          "subtitle": "Rome, Italy",
          "era": "1647–1669",
          "desc": "Where Plunkett studied and was ordained",
          "lat": 41.8951,
          "lng": 12.4822,
          "remote": true,
          "hasAudio": false,
          "hasAR": false,
          "audioSrc": null
        },
        {
          "id": "ghent",
          "name": "St Bavo's Cathedral",
          "subtitle": "Ghent, Belgium",
          "era": "1 December 1669",
          "desc": "One of his European postings during exile",
          "lat": 51.0536,
          "lng": 3.7196,
          "remote": true,
          "hasAudio": false,
          "hasAR": false,
          "audioSrc": null
        },
        {
          "id": "louvain",
          "name": "Irish College",
          "subtitle": "Louvain, Belgium",
          "era": "1669",
          "desc": "A key centre of Irish Catholic learning abroad",
          "lat": 50.8777,
          "lng": 4.7005,
          "remote": true,
          "hasAudio": false,
          "hasAR": false,
          "audioSrc": null
        },
        {
          "id": "london",
          "name": "Tyburn",
          "subtitle": "London, England",
          "era": "1 July 1681",
          "desc": "Where he was tried and executed, 1681",
          "lat": 51.5137,
          "lng": -0.1637,
          "remote": true,
          "hasAudio": false,
          "hasAR": false,
          "audioSrc": null
        },
        {
          "id": "lamspringe",
          "name": "Benedictine Monastery",
          "subtitle": "Lamspringe, Germany",
          "era": "1683–1883",
          "desc": "Where his body rested for two centuries",
          "lat": 51.9375,
          "lng": 9.9756,
          "remote": true,
          "hasAudio": false,
          "hasAR": false,
          "audioSrc": null
        }
      ]
    },
    {
      "id": "diaspora",
      "label": "Diaspora Trail",
      "color": "#8ec89a",
      "url": "https://streetsceal.ie/diaspora-trail.html",
      "desc": "Drogheda to Liverpool, Bordeaux and beyond — following the routes of those who left.",
      "stops": [
        {
          "id": "diaspora-quayside",
          "name": "The Quayside",
          "subtitle": "West Gate, River Boyne, Drogheda",
          "era": "18th–20th century",
          "desc": "The point of departure for emigrants leaving by sea",
          "lat": 53.713810,
          "lng": -6.348835,
          "remote": false,
          "hasAudio": false,
          "hasAR": true,
          "audioSrc": null,
          "linking": true
        },
        {
          "id": "diaspora-st-peters",
          "name": "St Peter's Church",
          "subtitle": "West Street, Drogheda",
          "era": "1921–present",
          "desc": "A place of farewell and last blessing before emigration",
          "lat": 53.715034,
          "lng": -6.352422,
          "remote": false,
          "hasAudio": false,
          "hasAR": true,
          "audioSrc": null,
          "linking": true
        },
        {
          "id": "scotland-road",
          "name": "Scotland Road",
          "subtitle": "Vauxhall, Liverpool, England",
          "era": "1840s–1960s",
          "desc": "The most common first landing point for Irish emigrants",
          "lat": 53.4133,
          "lng": -2.9768,
          "remote": true,
          "hasAudio": false,
          "hasAR": false,
          "audioSrc": null
        },
        {
          "id": "bordeaux-college",
          "name": "Irish College, Bordeaux",
          "subtitle": "Rue du Hâ, Bordeaux, France",
          "era": "1603–18th century",
          "desc": "A wine trade destination with deep Irish connections",
          "lat": 44.8378,
          "lng": -0.5792,
          "remote": true,
          "hasAudio": false,
          "hasAR": false,
          "audioSrc": null
        },
        {
          "id": "quai-chartrons",
          "name": "Quai des Chartrons",
          "subtitle": "Bordeaux, France",
          "era": "18th century–present",
          "desc": "The quay where Irish merchant families built their trade",
          "lat": 44.8470,
          "lng": -0.5680,
          "remote": true,
          "hasAudio": false,
          "hasAR": false,
          "audioSrc": null
        }
      ]
    },
    {
      "id": "megalithic",
      "label": "Megalithic Trail",
      "color": "#c87d6e",
      "url": "https://streetsceal.ie/megalithic-trail.html",
      "desc": "Five thousand years of continuous presence — Newgrange, Knowth, Dowth, Tara and Loughcrew.",
      "stops": [
        {
          "id": "megalithic-millmount",
          "name": "Millmount",
          "subtitle": "Millmount Square, Drogheda",
          "era": "Neolithic–present",
          "desc": "A Neolithic mound within the town itself — links to the Town Trail",
          "lat": 53.711665,
          "lng": -6.349454,
          "remote": false,
          "hasAudio": false,
          "hasAR": true,
          "audioSrc": null,
          "linking": true
        },
        {
          "id": "newgrange",
          "name": "Newgrange",
          "subtitle": "Brú na Bóinne, Co. Meath",
          "era": "c. 3200 BC",
          "desc": "Passage tomb older than Stonehenge — winter solstice aligned",
          "lat": 53.694692,
          "lng": -6.475402,
          "remote": true,
          "hasAudio": false,
          "hasAR": false,
          "audioSrc": null
        },
        {
          "id": "knowth",
          "name": "Knowth",
          "subtitle": "Brú na Bóinne, Co. Meath",
          "era": "c. 3200 BC",
          "desc": "The largest passage tomb in Ireland, surrounded by satellite mounds",
          "lat": 53.700958,
          "lng": -6.490358,
          "remote": true,
          "hasAudio": false,
          "hasAR": false,
          "audioSrc": null
        },
        {
          "id": "dowth",
          "name": "Dowth",
          "subtitle": "Brú na Bóinne, Co. Meath",
          "era": "c. 3200 BC",
          "desc": "The third great mound of the Brú na Bóinne complex",
          "lat": 53.703880,
          "lng": -6.450259,
          "remote": true,
          "hasAudio": false,
          "hasAR": false,
          "audioSrc": null
        },
        {
          "id": "fourknocks",
          "name": "Fourknocks",
          "subtitle": "Stamullen, Co. Meath",
          "era": "c. 2750 BC",
          "desc": "A Neolithic passage tomb with remarkable carved stone art",
          "lat": 53.596513,
          "lng": -6.326546,
          "remote": true,
          "hasAudio": false,
          "hasAR": false,
          "audioSrc": null
        },
        {
          "id": "tara",
          "name": "Hill of Tara",
          "subtitle": "Co. Meath",
          "era": "Neolithic–medieval",
          "desc": "The ancient seat of the High Kings of Ireland",
          "lat": 53.5775,
          "lng": -6.6119,
          "remote": true,
          "hasAudio": false,
          "hasAR": false,
          "audioSrc": null
        },
        {
          "id": "megalithic-loughcrew",
          "name": "Loughcrew",
          "subtitle": "Oldcastle, Co. Meath",
          "era": "c. 3300 BC",
          "desc": "A hilltop complex of passage tombs — the Hills of the Witch",
          "lat": 53.744459,
          "lng": -7.112099,
          "remote": true,
          "hasAudio": false,
          "hasAR": false,
          "audioSrc": null,
          "linking": true
        }
      ]
    }
  ]
}
